fennel_invest_api/__init__.py
fennel_invest_api/endpoints.py
fennel_invest_api/fennel.py
fennel_invest_api/utils.py
fennel_invest_api/models/__init__.py
fennel_invest_api/models/account_id_pb2.py
fennel_invest_api/models/account_id_pb2.pyi
fennel_invest_api/models/accounts_pb2.py
fennel_invest_api/models/accounts_pb2.pyi
fennel_invest_api/models/cancel_order_pb2.py
fennel_invest_api/models/cancel_order_pb2.pyi
fennel_invest_api/models/create_order_pb2.py
fennel_invest_api/models/create_order_pb2.pyi
fennel_invest_api/models/exception_pb2.py
fennel_invest_api/models/exception_pb2.pyi
fennel_invest_api/models/get_order_pb2.py
fennel_invest_api/models/get_order_pb2.pyi
fennel_invest_api/models/list_orders_pb2.py
fennel_invest_api/models/list_orders_pb2.pyi
fennel_invest_api/models/nbbo_pb2.py
fennel_invest_api/models/nbbo_pb2.pyi
fennel_invest_api/models/order_details_pb2.py
fennel_invest_api/models/order_details_pb2.pyi
fennel_invest_api/models/order_response_pb2.py
fennel_invest_api/models/order_response_pb2.pyi
fennel_invest_api/models/portfolio_summary_pb2.py
fennel_invest_api/models/portfolio_summary_pb2.pyi
fennel_invest_api/models/positions_pb2.py
fennel_invest_api/models/positions_pb2.pyi
fennel_invest_api/models/prices_pb2.py
fennel_invest_api/models/prices_pb2.pyi
fennel_invest_api-2.0.1.dist-info/licenses/LICENSE
fennel_invest_api-2.0.1.dist-info/METADATA
fennel_invest_api-2.0.1.dist-info/WHEEL
fennel_invest_api-2.0.1.dist-info/top_level.txt
fennel_invest_api-2.0.1.dist-info/RECORD
