Metadata-Version: 2.4
Name: fennel_invest_api
Version: 2.0.1
Summary: Unofficial Fennel.com Invest API written in Python Requests
Author: Nelson Dane
Project-URL: Homepage, https://github.com/NelsonDane/fennel-invest-api
Requires-Python: >=3.10
License-File: LICENSE
Requires-Dist: protobuf>=6.30.0
Requires-Dist: requests
Dynamic: license-file
